{
  "questions": [
    {
      "question": "How is the faction or organization structured?",
      "options": [
        "Hierarchical",
        "Decentralized",
        "Council-based",
        "Military-like",
        "Tribal",
        "Guild-like"
      ]
    },
    {
      "question": "What are the ranks within the organization?",
      "options": [
        "Initiate, Member, Senior Member, Leader",
        "Apprentice, Journeyman, Master, Grandmaster",
        "Footman, Sergeant, Lieutenant, Captain",
        "Novice, Adept, Expert, Archmage",
        "Scout, Hunter, Tracker, Ranger",
        "Scribe, Librarian, Scholar, Sage"
      ]
    },
    {
      "question": "How does one rise through the ranks?",
      "options": [
        "Completing quests or missions",
        "Proving loyalty and skill",
        "Through combat and duels",
        "Earning the favor of superiors",
        "Gaining knowledge or power",
        "Surviving trials or initiations"
      ]
    },
    {
      "question": "What are the responsibilities and privileges associated with each rank?",
      "options": [
        "Increased access to resources",
        "Commanding lower ranks",
        "Access to secret knowledge or magic",
        "Involvement in decision making",
        "Guarding important locations or people",
        "Leading missions or expeditions"
      ]
    },
    {
      "question": "Who are the key leaders and influential figures within the faction?",
      "options": [
        "The Grandmaster or Supreme Leader",
        "High-ranking wizards or clerics",
        "Veteran warriors or rogues",
        "Ancient beings or dragons",
        "Council of elders or advisors",
        "Founders or legendary heroes"
      ]
    },
    {
      "question": "What are the requirements for joining the faction?",
      "options": [
        "Proving one's skill in combat or magic",
        "Demonstrating loyalty or a shared goal",
        "Completing a dangerous task or quest",
        "Having a particular background or lineage",
        "Making a significant contribution or donation",
        "Being recommended by a current member"
      ]
    },
    {
      "question": "What benefits do members receive?",
      "options": [
        "Access to training and knowledge",
        "Protection and support from the faction",
        "Magical items or powerful equipment",
        "Financial support or wealth",
        "Influence and power",
        "Healing and recovery services"
      ]
    },
    {
      "question": "What obligations do members have to the faction?",
      "options": [
        "Following orders or missions",
        "Upholding the faction's code or ideals",
        "Contributing a portion of their earnings",
        "Participating in faction events or rituals",
        "Defending the faction's interests",
        "Keeping faction secrets"
      ]
    },
    {
      "question": "Are there any secret rites or initiation ceremonies?",
      "options": [
        "Ritual combat or trials",
        "Swearing oaths of loyalty",
        "Performing a significant task",
        "Undergoing a magical transformation",
        "Participating in a secret ritual",
        "Receiving a mark or symbol of the faction"
      ]
    },
    {
      "question": "How is loyalty to the faction ensured?",
      "options": [
        "Magical oaths or bindings",
        "Surveillance and monitoring",
        "Rewards for loyalty and punishment for betrayal",
        "Fostering a strong sense of camaraderie",
        "Threats or blackmail",
        "Cultural or ideological indoctrination"
      ]
    },
    {
      "question": "What are the long-term goals of the faction?",
      "options": [
        "World domination or control",
        "Protecting a particular region or people",
        "Gathering knowledge or magical power",
        "Destroying a common enemy",
        "Restoring an ancient order or kingdom",
        "Maintaining balance or peace"
      ]
    },
    {
      "question": "What are the faction's short-term objectives?",
      "options": [
        "Recruiting new members",
        "Acquiring resources or wealth",
        "Completing specific missions or quests",
        "Establishing new bases or strongholds",
        "Gathering intelligence or information",
        "Strengthening alliances or partnerships"
      ]
    },
    {
      "question": "How does the faction plan to achieve its goals?",
      "options": [
        "Through diplomacy and alliances",
        "Using covert operations and espionage",
        "Engaging in direct combat or warfare",
        "Employing magic or divine intervention",
        "Manipulating politics or economics",
        "Promoting cultural or ideological shifts"
      ]
    },
    {
      "question": "Are there any ideological differences within the faction?",
      "options": [
        "Differences in leadership approach",
        "Disagreements on goals and methods",
        "Rivalries between subgroups",
        "Varied interpretations of the faction's ideals",
        "Conflicts between traditionalists and reformists",
        "Differences in alignment or morality"
      ]
    },
    {
      "question": "What resources does the faction control (e.g., wealth, magical items, information)?",
      "options": [
        "Vast treasure hoards",
        "Powerful magical artifacts",
        "Extensive libraries of knowledge",
        "Strong military forces",
        "Control over trade routes or territories",
        "Influential political connections"
      ]
    },
    {
      "question": "Does the faction have any significant strongholds or bases of operation?",
      "options": [
        "Hidden fortresses or castles",
        "Secret underground lairs",
        "Magical towers or sanctuaries",
        "Remote islands or wilderness bases",
        "Ancient ruins or temples",
        "Urban headquarters or guildhalls"
      ]
    },
    {
      "question": "How does the faction fund its activities?",
      "options": [
        "Trade and commerce",
        "Plundering or raiding",
        "Taxes or tributes",
        "Donations and sponsorships",
        "Selling magical services or items",
        "Controlled businesses or enterprises"
      ]
    },
    {
      "question": "Are there any notable allies or patrons supporting the faction?",
      "options": [
        "Wealthy nobles or merchants",
        "Powerful wizards or clerics",
        "Other allied factions",
        "Dragons or other powerful creatures",
        "Governments or rulers",
        "Secret societies or cults"
      ]
    },
    {
      "question": "What methods does the faction use to achieve its goals?",
      "options": [
        "Espionage and intelligence gathering",
        "Assassinations and sabotage",
        "Political maneuvering and diplomacy",
        "Direct combat and military action",
        "Magical rituals and spells",
        "Propaganda and information warfare"
      ]
    },
    {
      "question": "How does the faction handle conflict or opposition?",
      "options": [
        "Negotiation and compromise",
        "Intimidation and threats",
        "Bribery and corruption",
        "Open warfare and battles",
        "Covert operations and sabotage",
        "Magical or divine retribution"
      ]
    },
    {
      "question": "Are there any forbidden practices or tactics?",
      "options": [
        "Use of dark or forbidden magic",
        "Attacking non-combatants",
        "Betrayal of allies",
        "Destruction of sacred sites",
        "Use of torture or extreme measures",
        "Consorting with fiends or undead"
      ]
    },
    {
      "question": "How does the faction gather information or intelligence?",
      "options": [
        "Spies and informants",
        "Divination magic",
        "Interrogation and questioning",
        "Infiltrating other organizations",
        "Scrying and surveillance",
        "Studying ancient texts or artifacts"
      ]
    },
    {
      "question": "How does the faction view and interact with other factions and organizations?",
      "options": [
        "Alliances based on mutual benefit",
        "Rivalries and competition",
        "Neutrality and non-interference",
        "Subterfuge and manipulation",
        "Diplomatic and trade relations",
        "Conflict and warfare"
      ]
    },
    {
      "question": "Are there any alliances or rivalries?",
      "options": [
        "Alliances with similar factions",
        "Rivalries with opposing factions",
        "Neutral stance towards most factions",
        "Secret alliances and pacts",
        "Long-standing feuds or grudges",
        "Temporary alliances of convenience"
      ]
    },
    {
      "question": "How does the faction handle negotiations or diplomacy?",
      "options": [
        "Through skilled diplomats or negotiators",
        "Using threats and intimidation",
        "Offering bribes or incentives",
        "Employing magical or divine persuasion",
        "Leveraging political or economic power",
        "Seeking common ground and compromise"
      ]
    },
    {
      "question": "What is the faction's public reputation versus its true nature?",
      "options": [
        "Respected but secretly corrupt",
        "Feared but protective",
        "Admired but ruthless",
        "Mistrusted but fair",
        "Beloved but manipulative",
        "Neutral but secretly ambitious"
      ]
    },
    {
      "question": "What is the faction's influence on the local and regional politics?",
      "options": [
        "Dominates local politics",
        "Influences regional decisions",
        "Minor but growing influence",
        "Acts behind the scenes",
        "Opposes the current rulers",
        "Supports the ruling powers"
      ]
    },
    {
      "question": "How does the faction impact the lives of ordinary people?",
      "options": [
        "Provides protection and security",
        "Demands taxes or tributes",
        "Offers aid and assistance",
        "Enforces strict laws or codes",
        "Inspires fear and obedience",
        "Promotes education and culture"
      ]
    },
    {
      "question": "What role does the faction play in the larger world?",
      "options": [
        "A major political force",
        "A secretive power behind the scenes",
        "A protector of ancient knowledge",
        "A relentless enemy of evil",
        "A broker of peace and diplomacy",
        "A driver of economic growth"
      ]
    },
    {
      "question": "Are there any notable events or incidents associated with the faction?",
      "options": [
        "Historic battles or wars",
        "Significant treaties or alliances",
        "Famous heroes or villains",
        "Legendary quests or adventures",
        "Mysterious disappearances",
        "Public scandals or betrayals"
      ]
    }
  ]
}
